tools/__init__.py
tools/config_loader.py
tools/crc.py
tools/emq_tool.py
tools/utils.py
w_tool-0.0.6.dist-info/LICENSE
w_tool-0.0.6.dist-info/METADATA
w_tool-0.0.6.dist-info/WHEEL
w_tool-0.0.6.dist-info/top_level.txt
w_tool-0.0.6.dist-info/RECORD
