Metadata-Version: 2.1
Name: w-tool
Version: 0.0.6
Summary: will's tool
Home-page: UNKNOWN
Author: will
Author-email: 420821129@qq.com
License: UNKNOWN
Platform: UNKNOWN
Classifier: Programming Language :: Python :: 3
Classifier: License :: OSI Approved :: MIT License
Classifier: Operating System :: OS Independent
Classifier: Operating System :: Microsoft :: Windows :: Windows 10
Requires-Python: >=3.6
License-File: LICENSE
